progressbar_tracker/__init__.py
progressbar_tracker-1.0.0.dist-info/licenses/LICENSE
progressbar_tracker-1.0.0.dist-info/METADATA
progressbar_tracker-1.0.0.dist-info/WHEEL
progressbar_tracker-1.0.0.dist-info/top_level.txt
progressbar_tracker-1.0.0.dist-info/RECORD
