Metadata-Version: 2.4
Name: progressbar-tracker
Version: 1.0.0
Summary: Python SDK for Progress Bar Tracker - Track and manage progress bars with read/write/admin permissions
Author-email: Haotian <yht0511@users.noreply.github.com>
License: MIT
Project-URL: Homepage, https://github.com/yht0511/progressbar
Project-URL: Repository, https://github.com/yht0511/progressbar
Project-URL: Issues, https://github.com/yht0511/progressbar/issues
Keywords: progress,tracker,progress-bar,task-management,monitoring
Classifier: Development Status :: 4 - Beta
Classifier: Intended Audience :: Developers
Classifier: License :: OSI Approved :: MIT License
Classifier: Programming Language :: Python :: 3
Classifier: Programming Language :: Python :: 3.7
Classifier: Programming Language :: Python :: 3.8
Classifier: Programming Language :: Python :: 3.9
Classifier: Programming Language :: Python :: 3.10
Classifier: Programming Language :: Python :: 3.11
Classifier: Programming Language :: Python :: 3.12
Classifier: Topic :: Software Development :: Libraries :: Python Modules
Classifier: Topic :: System :: Monitoring
Requires-Python: >=3.7
License-File: LICENSE
Requires-Dist: requests>=2.25.0
Dynamic: license-file
